LICENSE
restx/__init__.py
restx/cli.py
restx/enums.py
restx/utils.py
restx-0.1.13.dist-info/LICENSE
restx-0.1.13.dist-info/METADATA
restx-0.1.13.dist-info/WHEEL
restx-0.1.13.dist-info/entry_points.txt
restx-0.1.13.dist-info/RECORD
